pydockercompose/DockerCompose.py
pydockercompose/Service.py
pydockercompose/__init__.py
pydockercompose-0.1.0.dist-info/LICENSE
pydockercompose-0.1.0.dist-info/METADATA
pydockercompose-0.1.0.dist-info/WHEEL
pydockercompose-0.1.0.dist-info/top_level.txt
pydockercompose-0.1.0.dist-info/RECORD
