Metadata-Version: 2.1
Name: pydockercompose
Version: 0.1.0
Summary: Package to generate docker compose files.
Home-page: https://github.com/DadiAnas/pydockercompose
Author: Anas Dadi
Author-email: dadi.anas@hotmail.fr
License: UNKNOWN
Project-URL: Bug Tracker, https://github.com/DadiAnas/pydockercompose/issues
Platform: UNKNOWN
Classifier: Programming Language :: Python :: 3
Classifier: License :: OSI Approved :: MIT License
Classifier: Operating System :: OS Independent
Requires-Python: >=3.0
License-File: LICENSE
